trendup_config/__init__.py
trendup_config/file_config.py
trendup_config/yaml_config.py
trendup_storage/__init__.py
trendup_storage/file.py
trendup_storage/file_storage.py
trendup_storage/local_storage.py
trendup_storage/models.py
trendup_storage/image/__init__.py
trendup_storage/image/image_storage.py
trendup_storage/image/image_storage_impl.py
trendup_storage/image/image_storage_mock.py
trendup_utils/__init__.py
trendup_utils/temp_file.py
trendup_utils/temp_file_impl.py
trendup_video/__init__.py
trendup_video/recorded_video.py
trendup_video/type_alias.py
trendup_video/video_data.py
trendup_video/web_recorded_video.py
trendup_video/download/__init__.py
trendup_video/download/download_video.py
trendup_video/download/download_video_impl.py
trendup_video/reader/__init__.py
trendup_video/reader/video_reader.py
trendup_video/reader/video_reader_cv.py
trendup_video/reader/video_reader_mock.py
trendup_video/web/__init__.py
trendup_video/web/pre_handle_video.py
trendup_video/web/pre_handle_video_impl.py
trendup_video/web/pre_handle_video_mock.py
trendup_python_lib-0.1.5.dist-info/METADATA
trendup_python_lib-0.1.5.dist-info/WHEEL
trendup_python_lib-0.1.5.dist-info/top_level.txt
trendup_python_lib-0.1.5.dist-info/RECORD
