Metadata-Version: 2.1
Name: trendup-python-lib
Version: 0.1.5
Summary: trendup library
Home-page: https://www.keeptossinglab.com/trendup-me
Author: JerryLin
Author-email: jerry.lin@keeptossinglab.com
Classifier: Programming Language :: Python :: 3
Classifier: License :: OSI Approved :: MIT License
Requires-Dist: attrs
Requires-Dist: pyyaml
Requires-Dist: numpy
Requires-Dist: opencv-python
